[
    {
        "con": "Crt",
        "mag": 3.56,
        "x": 0.0,
        "y": 0.0,
        "z": 0.0
    },
    {
        "con": "Crt",
        "mag": 4.06,
        "x": -0.027892134794958556,
        "y": 0.9999999999999999,
        "z": 7.845848383190494e-17
    },
    {
        "con": "Crt",
        "mag": 4.08,
        "x": -0.09383494268410528,
        "y": 0.41733503182049875,
        "z": -1.7843350917860528
    },
    {
        "con": "Crt",
        "mag": 4.46,
        "x": -0.18564201516295586,
        "y": 2.0601542542449947,
        "z": -1.5434349366546767
    },
    {
        "con": "Crt",
        "mag": 4.7,
        "x": -0.11653030350951211,
        "y": -0.8531520227442826,
        "z": 1.8546411398294569
    },
    {
        "con": "Crt",
        "mag": 4.71,
        "x": -0.13604396553047338,
        "y": 1.8210822705877123,
        "z": 1.243562929145928
    },
    {
        "con": "Crt",
        "mag": 4.81,
        "x": -0.04645681663228495,
        "y": -0.9481682382703024,
        "z": 0.8750445432336387
    },
    {
        "con": "Crt",
        "mag": 5.08,
        "x": -0.04626393894030614,
        "y": 1.2638393421732086,
        "z": -0.2460354720980811
    },
    {
        "con": "Crt",
        "mag": 5.17,
        "x": -0.22715360628123438,
        "y": 1.855830876842901,
        "z": 2.1574593771803245
    },
    {
        "con": "Crt",
        "mag": 5.48,
        "x": -0.0668013118807735,
        "y": 0.17283136396256013,
        "z": 1.537048324889047
    },
    {
        "con": "Crt",
        "mag": 5.51,
        "x": -0.07490500872694661,
        "y": -1.490207106365769,
        "z": -0.6791801575370133
    },
    {
        "con": "Crt",
        "mag": 5.65,
        "x": -0.10334670835922603,
        "y": -1.0521194414230737,
        "z": -1.6094950525098286
    },
    {
        "con": "Crt",
        "mag": 5.77,
        "x": -0.27166750170057596,
        "y": 3.0555676764945505,
        "z": -0.58070003040672
    },
    {
        "con": "Crt",
        "mag": 5.86,
        "x": -0.05999720950367618,
        "y": -0.7841091386210935,
        "z": -1.2386648678317338
    },
    {
        "con": "Crt",
        "mag": 5.88,
        "x": -0.06901698080791333,
        "y": -0.15055070531878523,
        "z": -1.564902757571029
    },
    {
        "con": "Crt",
        "mag": 5.93,
        "x": -0.025881168469661008,
        "y": -0.4409799154123323,
        "z": 0.8564407681627725
    },
    {
        "con": "Crt",
        "mag": 5.94,
        "x": -0.16145231539065974,
        "y": -1.5391742838353848,
        "z": 1.8433209349304667
    }
]