[
    {
        "con": "PsA",
        "mag": 1.17,
        "x": 6.450517,
        "y": -1.799476,
        "z": -3.807757
    },
    {
        "con": "PsA",
        "mag": 4.18,
        "x": 125.047058,
        "y": -45.108691,
        "z": -67.860991
    },
    {
        "con": "PsA",
        "mag": 4.2,
        "x": 38.294356,
        "y": -10.990075,
        "z": -25.419746
    },
    {
        "con": "PsA",
        "mag": 4.29,
        "x": 34.265767,
        "y": -13.930345,
        "z": -23.425222
    },
    {
        "con": "PsA",
        "mag": 4.35,
        "x": 43.645415,
        "y": -29.177583,
        "z": -34.127517
    },
    {
        "con": "PsA",
        "mag": 4.46,
        "x": 53.085686,
        "y": -16.096898,
        "z": -35.853148
    },
    {
        "con": "PsA",
        "mag": 4.5,
        "x": 30.872906,
        "y": -16.349212,
        "z": -22.676862
    },
    {
        "con": "PsA",
        "mag": 4.94,
        "x": 13.670951,
        "y": -7.105556,
        "z": -9.83382
    },
    {
        "con": "PsA",
        "mag": 4.99,
        "x": 95.234327,
        "y": -50.406849,
        "z": -72.799456
    }
]