[
    {
        "con": "TrA",
        "mag": 1.91,
        "x": -13.127447,
        "y": -40.804561,
        "z": -111.826781
    },
    {
        "con": "TrA",
        "mag": 2.83,
        "x": -2.869157,
        "y": -4.734869,
        "z": -11.070637
    },
    {
        "con": "TrA",
        "mag": 2.87,
        "x": -13.248562,
        "y": -15.637336,
        "z": -52.51191
    },
    {
        "con": "TrA",
        "mag": 3.86,
        "x": -36.369544,
        "y": -74.106715,
        "z": -166.92277
    },
    {
        "con": "TrA",
        "mag": 4.11,
        "x": -14.537768,
        "y": -20.142359,
        "z": -56.634489
    },
    {
        "con": "TrA",
        "mag": 4.9,
        "x": -1.604938,
        "y": -3.802618,
        "z": -11.392224
    },
    {
        "con": "TrA",
        "mag": 5.1,
        "x": -26.142759,
        "y": -78.894233,
        "z": -196.84852
    },
    {
        "con": "TrA",
        "mag": 5.11,
        "x": -69.848616,
        "y": -115.667606,
        "z": -344.842643
    },
    {
        "con": "TrA",
        "mag": 5.19,
        "x": -43.431308,
        "y": -105.926299,
        "z": -212.030562
    },
    {
        "con": "TrA",
        "mag": 5.28,
        "x": -6.635916,
        "y": -15.624846,
        "z": -34.894668
    },
    {
        "con": "TrA",
        "mag": 5.5,
        "x": -15.641815,
        "y": -40.614242,
        "z": -95.48046
    },
    {
        "con": "TrA",
        "mag": 5.54,
        "x": -25.367599,
        "y": -39.019526,
        "z": -101.852305
    },
    {
        "con": "TrA",
        "mag": 5.71,
        "x": -55.524303,
        "y": -70.781845,
        "z": -188.874775
    },
    {
        "con": "TrA",
        "mag": 5.74,
        "x": -57.943788,
        "y": -99.327087,
        "z": -247.025878
    },
    {
        "con": "TrA",
        "mag": 5.75,
        "x": -81.082514,
        "y": -91.905034,
        "z": -338.189195
    },
    {
        "con": "TrA",
        "mag": 5.76,
        "x": -26368.815655,
        "y": -28650.408951,
        "z": -92107.761041
    },
    {
        "con": "TrA",
        "mag": 5.76,
        "x": -16.737421,
        "y": -27.882903,
        "z": -57.439191
    },
    {
        "con": "TrA",
        "mag": 5.79,
        "x": -22.286933,
        "y": -82.550332,
        "z": -225.905185
    },
    {
        "con": "TrA",
        "mag": 5.89,
        "x": -24.135595,
        "y": -30.409373,
        "z": -97.604364
    },
    {
        "con": "TrA",
        "mag": 5.89,
        "x": -25.229122,
        "y": -70.641963,
        "z": -188.459632
    },
    {
        "con": "TrA",
        "mag": 5.95,
        "x": -8.51307,
        "y": -17.667188,
        "z": -48.396746
    }
]