[
    {
        "con": "UMi",
        "mag": 1.97,
        "x": 1.3431,
        "y": 1.047629,
        "z": 132.614909
    },
    {
        "con": "UMi",
        "mag": 2.07,
        "x": -8.058164,
        "y": -7.429707,
        "z": 38.619407
    },
    {
        "con": "UMi",
        "mag": 3.0,
        "x": -29.797327,
        "y": -35.741213,
        "z": 141.814461
    },
    {
        "con": "UMi",
        "mag": 4.21,
        "x": -4.098102,
        "y": -12.242736,
        "z": 92.297935
    },
    {
        "con": "UMi",
        "mag": 4.25,
        "x": -21.740786,
        "y": -16.312428,
        "z": 106.600575
    },
    {
        "con": "UMi",
        "mag": 4.29,
        "x": -13.368655,
        "y": -19.830791,
        "z": 110.565025
    },
    {
        "con": "UMi",
        "mag": 4.35,
        "x": -0.379972,
        "y": -3.119005,
        "z": 52.676703
    },
    {
        "con": "UMi",
        "mag": 4.63,
        "x": -41.041157,
        "y": -40.184665,
        "z": 128.600839
    },
    {
        "con": "UMi",
        "mag": 4.8,
        "x": -25.551841,
        "y": -16.098449,
        "z": 136.761257
    },
    {
        "con": "UMi",
        "mag": 4.95,
        "x": -3.16421,
        "y": -6.597182,
        "z": 28.821068
    }
]