[
    {
        "con": "Vul",
        "mag": 4.44,
        "x": 0.0,
        "y": 0.0,
        "z": 0.0
    },
    {
        "con": "Vul",
        "mag": 4.5,
        "x": -0.0963561774160476,
        "y": 1.0,
        "z": 1.4319374123195266e-17
    },
    {
        "con": "Vul",
        "mag": 4.56,
        "x": -0.28232498492244845,
        "y": 1.6826836579878142,
        "z": -0.2146775281420036
    },
    {
        "con": "Vul",
        "mag": 4.57,
        "x": -0.025599034682373328,
        "y": 0.47316231658049784,
        "z": -0.20880531762541954
    },
    {
        "con": "Vul",
        "mag": 4.66,
        "x": -0.049615136571100116,
        "y": 0.7157376576479509,
        "z": 0.07037459621302462
    },
    {
        "con": "Vul",
        "mag": 4.76,
        "x": -0.015127948892005251,
        "y": -0.3480954724658207,
        "z": -0.19250625936912963
    },
    {
        "con": "Vul",
        "mag": 4.79,
        "x": -0.08896019776623143,
        "y": 0.9412960890747745,
        "z": -0.19458403583781497
    },
    {
        "con": "Vul",
        "mag": 4.81,
        "x": -0.2138736689132777,
        "y": 1.310272286892716,
        "z": -0.6911354271372651
    },
    {
        "con": "Vul",
        "mag": 4.9,
        "x": -0.024267658052295422,
        "y": 0.3863889237368498,
        "z": -0.3229654795980929
    },
    {
        "con": "Vul",
        "mag": 4.92,
        "x": -0.23581664556516838,
        "y": 1.5132451624690655,
        "z": -0.35290973652377866
    },
    {
        "con": "Vul",
        "mag": 5.0,
        "x": -0.020546388405789984,
        "y": -0.027064673587412238,
        "z": -0.46266495887245085
    },
    {
        "con": "Vul",
        "mag": 5.03,
        "x": -0.3004585286841958,
        "y": 1.7430826007933655,
        "z": -0.13618362825307165
    },
    {
        "con": "Vul",
        "mag": 5.06,
        "x": -0.2003071741687159,
        "y": 1.3681554596800258,
        "z": -0.431449616619055
    },
    {
        "con": "Vul",
        "mag": 5.08,
        "x": -0.06126838173372649,
        "y": 0.7292837303985003,
        "z": -0.3258039166636447
    },
    {
        "con": "Vul",
        "mag": 5.14,
        "x": -0.019324661941568982,
        "y": -0.21138797287533256,
        "z": -0.396684006923023
    },
    {
        "con": "Vul",
        "mag": 5.18,
        "x": -0.09173984642090241,
        "y": 0.8988527112862855,
        "z": -0.3802344998855664
    },
    {
        "con": "Vul",
        "mag": 5.19,
        "x": -0.0950875757182035,
        "y": 0.9897666973639161,
        "z": 0.08553805799046267
    },
    {
        "con": "Vul",
        "mag": 5.22,
        "x": -0.0034294604338785156,
        "y": -0.06521946478755776,
        "z": 0.17792303165638335
    },
    {
        "con": "Vul",
        "mag": 5.23,
        "x": -0.045585211978889165,
        "y": 0.6648885445842627,
        "z": -0.18256049482488604
    },
    {
        "con": "Vul",
        "mag": 5.3,
        "x": -0.09482260634174862,
        "y": 0.9506373774878762,
        "z": -0.2837575461249592
    },
    {
        "con": "Vul",
        "mag": 5.3,
        "x": -0.3363199156979911,
        "y": 1.7230660809320897,
        "z": -0.6638683599917641
    },
    {
        "con": "Vul",
        "mag": 5.39,
        "x": -0.5624356923323172,
        "y": 2.346663607910874,
        "z": -0.26091909818303294
    },
    {
        "con": "Vul",
        "mag": 5.46,
        "x": -0.007168041877096689,
        "y": -0.26643983054004505,
        "z": -0.06356272026715261
    },
    {
        "con": "Vul",
        "mag": 5.5,
        "x": -0.01016636724797191,
        "y": 0.3261613754067359,
        "z": -0.0017884938506989845
    },
    {
        "con": "Vul",
        "mag": 5.5,
        "x": -0.1169081455157679,
        "y": 1.0499637445857015,
        "z": -0.32934039062895587
    },
    {
        "con": "Vul",
        "mag": 5.51,
        "x": -0.07457665158047651,
        "y": 0.8789837897632486,
        "z": -0.05459210855106911
    },
    {
        "con": "Vul",
        "mag": 5.51,
        "x": -0.07854053110911084,
        "y": 0.9009425602814525,
        "z": -0.06934041669497186
    },
    {
        "con": "Vul",
        "mag": 5.54,
        "x": -0.02239984369616208,
        "y": 0.46864873013345076,
        "z": -0.12039177843218825
    },
    {
        "con": "Vul",
        "mag": 5.56,
        "x": -0.027574371099437032,
        "y": 0.5004198129765769,
        "z": -0.19403069534275222
    },
    {
        "con": "Vul",
        "mag": 5.59,
        "x": -0.1907815209412119,
        "y": 1.3839840147862594,
        "z": -0.21572002602335488
    },
    {
        "con": "Vul",
        "mag": 5.6,
        "x": -0.016892728761655346,
        "y": -0.18725558922179877,
        "z": -0.37628868064631676
    },
    {
        "con": "Vul",
        "mag": 5.66,
        "x": -0.28067884697715156,
        "y": 1.688020145448369,
        "z": -0.10854954155900995
    },
    {
        "con": "Vul",
        "mag": 5.67,
        "x": -0.5361109397551719,
        "y": 2.275880189991694,
        "z": -0.3853026075208923
    },
    {
        "con": "Vul",
        "mag": 5.68,
        "x": -0.040584015848808434,
        "y": 0.5620776766350555,
        "z": -0.3279018554937668
    },
    {
        "con": "Vul",
        "mag": 5.68,
        "x": -0.1446457552540896,
        "y": 1.0559704331514717,
        "z": -0.6157098456929807
    },
    {
        "con": "Vul",
        "mag": 5.7,
        "x": -0.5374671555547617,
        "y": 2.243069957672923,
        "z": -0.5563053179219168
    },
    {
        "con": "Vul",
        "mag": 5.78,
        "x": -0.020233818206627924,
        "y": -0.4429814318772217,
        "z": 0.12368320921896478
    },
    {
        "con": "Vul",
        "mag": 5.82,
        "x": -1.108478828205724e-05,
        "y": 0.007935481968026131,
        "z": 0.0072894318870646325
    },
    {
        "con": "Vul",
        "mag": 5.84,
        "x": -0.018376360863256516,
        "y": -0.18827552408467646,
        "z": -0.3958511824914292
    },
    {
        "con": "Vul",
        "mag": 5.88,
        "x": -0.04483315704642068,
        "y": 0.6559720843809153,
        "z": -0.193122557384174
    },
    {
        "con": "Vul",
        "mag": 5.89,
        "x": -0.0033254284985739526,
        "y": 0.10985574787630323,
        "z": 0.15084070003395808
    },
    {
        "con": "Vul",
        "mag": 5.91,
        "x": -0.07845391095625902,
        "y": 0.8975981179787454,
        "z": -0.09964689382486516
    },
    {
        "con": "Vul",
        "mag": 5.91,
        "x": -0.20180731651359565,
        "y": 1.3607689403378047,
        "z": -0.4705486834913962
    }
]